fast_robotstxt-1.1.0.dist-info/RECORD
fast_robotstxt-1.1.0.dist-info/WHEEL
fast_robotstxt-1.1.0.dist-info/METADATA
robotstxt/__init__.py
robotstxt/librobots.dylib
robotstxt/robots.py
robotstxt/include/ada_c.h
robotstxt/include/ada.h
robotstxt/include/ada/url_search_params.h
robotstxt/include/ada/ada_idna.h
robotstxt/include/ada/url_base-inl.h
robotstxt/include/ada/url_pattern_regex.h
robotstxt/include/ada/encoding_type.h
robotstxt/include/ada/unicode-inl.h
robotstxt/include/ada/url_aggregator.h
robotstxt/include/ada/ada_version.h
robotstxt/include/ada/checkers-inl.h
robotstxt/include/ada/parser.h
robotstxt/include/ada/url_components-inl.h
robotstxt/include/ada/character_sets-inl.h
robotstxt/include/ada/implementation-inl.h
robotstxt/include/ada/character_sets.h
robotstxt/include/ada/errors.h
robotstxt/include/ada/url_aggregator-inl.h
robotstxt/include/ada/scheme.h
robotstxt/include/ada/url_components.h
robotstxt/include/ada/url_pattern-inl.h
robotstxt/include/ada/implementation.h
robotstxt/include/ada/unicode.h
robotstxt/include/ada/url_base.h
robotstxt/include/ada/scheme-inl.h
robotstxt/include/ada/url_pattern.h
robotstxt/include/ada/common_defs.h
robotstxt/include/ada/log.h
robotstxt/include/ada/url.h
robotstxt/include/ada/url-inl.h
robotstxt/include/ada/url_pattern_helpers-inl.h
robotstxt/include/ada/expected.h
robotstxt/include/ada/url_search_params-inl.h
robotstxt/include/ada/checkers.h
robotstxt/include/ada/parser-inl.h
robotstxt/include/ada/url_pattern_init.h
robotstxt/include/ada/url_pattern_helpers.h
robotstxt/include/ada/state.h
robotstxt/include/ada/helpers.h
robotstxt/include/ada/serializers.h
robotstxt/lib/libada.a
robotstxt/lib/pkgconfig/ada.pc
robotstxt/lib/cmake/ada/ada_targets-release.cmake
robotstxt/lib/cmake/ada/ada-config.cmake
robotstxt/lib/cmake/ada/ada-config-version.cmake
robotstxt/lib/cmake/ada/ada_targets.cmake
