Metadata-Version: 2.2
Name: fast-robotstxt
Version: 1.1.0
Summary: Python bindings for Google's robots.txt parser library
Keywords: robots.txt,robots,crawler,parser,web,seo,googlebot
Author: Google LLC
Author-Email: Alexey Nazarov <nz@nzrsky.com>
License: Apache-2.0
Classifier: Development Status :: 5 - Production/Stable
Classifier: Intended Audience :: Developers
Classifier: License :: OSI Approved :: Apache Software License
Classifier: Operating System :: MacOS :: MacOS X
Classifier: Operating System :: Microsoft :: Windows
Classifier: Operating System :: POSIX :: Linux
Classifier: Programming Language :: Python :: 3
Classifier: Programming Language :: Python :: 3.8
Classifier: Programming Language :: Python :: 3.9
Classifier: Programming Language :: Python :: 3.10
Classifier: Programming Language :: Python :: 3.11
Classifier: Programming Language :: Python :: 3.12
Classifier: Programming Language :: Python :: 3.13
Classifier: Programming Language :: C++
Classifier: Topic :: Internet :: WWW/HTTP
Classifier: Topic :: Software Development :: Libraries
Project-URL: Homepage, https://github.com/nzrsky/robotstxt
Project-URL: Repository, https://github.com/nzrsky/robotstxt
Project-URL: Documentation, https://github.com/nzrsky/robotstxt#readme
Project-URL: Issues, https://github.com/nzrsky/robotstxt/issues
Requires-Python: >=3.8
